{
  "search_query": {
    "query_id": "q.q.mjq1ftlyodu0",
    "text": "telegram отправить сообщение",
    "filters": {
      "capability": [
        "send_message"
      ],
      "platform": [
        "android"
      ],
      "risk": [
        "low"
      ]
    },
    "sort": {
      "by": "relevance",
      "order": "desc"
    },
    "paging": {
      "offset": 0,
      "limit": 10
    },
    "context": {
      "lang": "ru",
      "platform": "android",
      "policy_mode": "balanced",
      "user_role": "novice"
    },
    "version": "1.0.0"
  },
  "ranking_profile": {
    "profile_id": "rp.r.tkk2se8v9hao",
    "weights": {
      "text_relevance": 0.45,
      "dq_overall": 0.15,
      "trust": 0.1,
      "installability": 0.1,
      "success_rate": 0.12,
      "freshness": 0.04,
      "popularity": 0.04
    },
    "rules": [
      {
        "kind": "boost",
        "when": {
          "one_click_ready": true
        },
        "effect": {
          "boost": 0.15
        }
      },
      {
        "kind": "penalty",
        "when": {
          "risk": "high"
        },
        "effect": {
          "penalty": 0.25
        }
      }
    ],
    "version": "1.0.0"
  },
  "synonyms": {
    "syn_id": "syn.s.32o098ci9oph",
    "lang": "ru",
    "pairs": [
      {
        "from": "интегромат",
        "to": [
          "make",
          "make.com"
        ]
      },
      {
        "from": "телега",
        "to": [
          "telegram"
        ]
      },
      {
        "from": "письмо",
        "to": [
          "email",
          "smtp"
        ]
      }
    ],
    "version": "1.0.0"
  },
  "vitrine": {
    "vitrine_id": "vit.v.xjlh9v2gp5zy",
    "title": "Android: Автоматизация без сервера — стартовый набор",
    "kind": "hybrid",
    "criteria": {
      "platform": "android",
      "min_success_rate": 0.8,
      "min_dq": 0.7
    },
    "items": [
      {
        "canonical_id": "canon.telegram_send_message",
        "position": 1,
        "reason": "one-click + high success",
        "requirements": {
          "platform": "android"
        },
        "one_click_ready": true,
        "version": "1.0.0"
      },
      {
        "canonical_id": "canon.rss_to_telegram",
        "position": 2,
        "reason": "popular automation",
        "requirements": {
          "platform": "android"
        },
        "one_click_ready": false,
        "version": "1.0.0"
      }
    ],
    "updated_at": "2026-01-03T11:26:00Z",
    "version": "1.0.0"
  },
  "feedback_event": {
    "event_id": "ev.e.b8hhkc2yjx2u",
    "event_type": "run_success",
    "canonical_id": "canon.telegram_send_message",
    "ts": "2026-01-03T11:26:00Z",
    "context": {
      "platform": "android",
      "policy_mode": "balanced",
      "lang": "ru"
    },
    "value": {
      "duration_ms": 850,
      "cost": 0.0
    },
    "version": "1.0.0"
  },
  "ab_test": {
    "test_id": "ab.t.z8i0lwsi0wzp",
    "name": "RankingProfile A vs B",
    "variants": [
      {
        "id": "A",
        "ranking_profile_id": "rp.r.tkk2se8v9hao",
        "traffic": 0.5
      },
      {
        "id": "B",
        "ranking_profile_id": "rp.alt_profile",
        "traffic": 0.5
      }
    ],
    "metrics": [
      "ctr",
      "install_rate",
      "run_success_rate",
      "time_to_value"
    ],
    "guardrails": [
      "complaints",
      "cost_per_success"
    ],
    "status": "running",
    "version": "1.0.0"
  }
}